setup.py
socialsent/__init__.py
socialsent/constants.py
socialsent/embedding_transformer.py
socialsent/evaluate_methods.py
socialsent/graph_construction.py
socialsent/lexicons.py
socialsent/polarity_induction_methods.py
socialsent/seeds.py
socialsent/util.py
socialsent.egg-info/PKG-INFO
socialsent.egg-info/SOURCES.txt
socialsent.egg-info/dependency_links.txt
socialsent.egg-info/not-zip-safe
socialsent.egg-info/requires.txt
socialsent.egg-info/top_level.txt
socialsent/data/lexicons/140-scores.json
socialsent/data/lexicons/bingliu.json
socialsent/data/lexicons/concreteness.json
socialsent/data/lexicons/finance.json
socialsent/data/lexicons/inquirer.json
socialsent/data/lexicons/kuperman.json
socialsent/data/lexicons/mpqa.json
socialsent/data/lexicons/qwn-scores.json
socialsent/data/lexicons/qwn.json
socialsent/data/lexicons/qwn2.json
socialsent/data/lexicons/twitter-scores.json
socialsent/data/lexicons/twitter.json