Metadata-Version: 1.0
Name: socialsent
Version: 0.1.3
Summary: Algorithms for inducing domain-specific sentiment lexicons from unlabeled corpora.
Home-page: https://github.com/williamleif/socialsent
Author: William Hamilton
Author-email: wleif@stanford.edu
License: Apache Version 2
Platform: UNKNOWN
